MANIFEST.in
README.txt
etm_qt
setup.py
etmQt/CHANGES
etmQt/HEADER.html
etmQt/INSTALL.html
etmQt/README.html
etmQt/__init__.py
etmQt/etmData.py
etmQt/etmDiff.py
etmQt/etmReport.py
etmQt/etmView.py
etmQt/etmWeather.py
etmQt/etm_qt.1
etmQt/etm_qt.xpm
etmQt/profile.py
etmQt/qrc_etm copy.py
etmQt/qrc_etm.py
etmQt/v.py
etmQt/version.txt
etmQt/applications/etm_qt.desktop
etmQt/help/HEADER.html
etmQt/help/data.html
etmQt/help/help.html
etmQt/help/overview.html
etmQt/help/preferences.html
etmQt/help/reports.html
etmQt/help/shortcuts.html
etmQt/help/using_mercurial.html
etmQt/help/views.html
etmQt/help/images/12monthcalendar.png
etmQt/help/images/about.png
etmQt/help/images/action_export0.png
etmQt/help/images/action_export2.png
etmQt/help/images/action_export3.png
etmQt/help/images/action_finish.png
etmQt/help/images/action_pause.png
etmQt/help/images/action_report0.png
etmQt/help/images/action_report2.png
etmQt/help/images/action_report3.png
etmQt/help/images/action_restart.png
etmQt/help/images/action_running.png
etmQt/help/images/action_start.png
etmQt/help/images/agenda.png
etmQt/help/images/busy_times.png
etmQt/help/images/calendar_selection.png
etmQt/help/images/completion.png
etmQt/help/images/completion1.png
etmQt/help/images/completion2.png
etmQt/help/images/completions1.png
etmQt/help/images/completions2.png
etmQt/help/images/context_completion.png
etmQt/help/images/current.png
etmQt/help/images/date_calculator1.png
etmQt/help/images/date_calculator2.png
etmQt/help/images/date_calculator3.png
etmQt/help/images/date_calculator4.png
etmQt/help/images/day_view.png
etmQt/help/images/details_view.png
etmQt/help/images/detailsview.png
etmQt/help/images/doghouse1.png
etmQt/help/images/doghouse2.png
etmQt/help/images/folder_view1.png
etmQt/help/images/folder_view2.png
etmQt/help/images/highlighting.png
etmQt/help/images/mainview.png
etmQt/help/images/month_view.png
etmQt/help/images/pattern_filter1.png
etmQt/help/images/pattern_filter2.png
etmQt/help/images/paybills1.png
etm_qt.egg-info/PKG-INFO
etm_qt.egg-info/SOURCES.txt
etm_qt.egg-info/dependency_links.txt
etm_qt.egg-info/not-zip-safe
etm_qt.egg-info/requires.txt
etm_qt.egg-info/top_level.txt